niobium/__init__.py
niobium/find_image.py
niobium/image_element.py
niobium/patch.py
niobium/timeout.py
niobium/webelement_action.py
niobium/webelement_wait.py
niobium-1.0.0.dist-info/licenses/LICENSE
niobium-1.0.0.dist-info/METADATA
niobium-1.0.0.dist-info/WHEEL
niobium-1.0.0.dist-info/top_level.txt
niobium-1.0.0.dist-info/RECORD
