Metadata-Version: 2.4
Name: niobium
Version: 1.0.0
Summary: Niobium extends the Python Selenium client with nice features
Author-email: cle-b <cle@tictac.pm>
License: Apache-2.0
Project-URL: Repository, https://github.com/cle-b/niobium/
Project-URL: Documentation, https://niobium.readthedocs.io/
Classifier: Programming Language :: Python :: 3
Classifier: License :: OSI Approved :: Apache Software License
Classifier: Operating System :: OS Independent
Classifier: Topic :: Software Development :: Testing
Classifier: Topic :: Software Development :: User Interfaces
Requires-Python: >=3.8
License-File: LICENSE
Requires-Dist: selenium>=4
Requires-Dist: opencv-python
Requires-Dist: pillow
Dynamic: license-file
